ncducolors/__init__.py
ncducolors/__main__.py
ncducolors/attribute.py
ncducolors/color.py
ncducolors/config.py
ncducolors/key.py
ncducolors/ncducolors.py
ncducolors/sequence.py
ncducolors/theme.py
ncducolors/utils.py
NcduColors-0.0.2.dist-info/LICENSE.txt
NcduColors-0.0.2.dist-info/METADATA
NcduColors-0.0.2.dist-info/WHEEL
NcduColors-0.0.2.dist-info/entry_points.txt
NcduColors-0.0.2.dist-info/top_level.txt
NcduColors-0.0.2.dist-info/RECORD
