Metadata-Version: 2.1
Name: NcduColors
Version: 0.0.2
Summary: Ncdu themes patcher
Home-page: https://github.com/Midblyte/NcduColors
Author: Midblyte
Author-email: ncducolors@midblyte.anonaddy.me
License: MIT
Project-URL: Source, https://github.com/Midblyte/NcduColors
Project-URL: Documentation, https://github.com/Midblyte/NcduColors#how-to-use
Project-URL: Tracker, https://github.com/Midblyte/NcduColors/issues
Keywords: ncdu themes
Classifier: Development Status :: 3 - Alpha
Classifier: Environment :: Console
Classifier: Intended Audience :: Developers
Classifier: Intended Audience :: End Users/Desktop
Classifier: License :: OSI Approved :: MIT License
Classifier: Operating System :: POSIX :: Linux
Classifier: Programming Language :: Python
Classifier: Programming Language :: Python :: 3
Classifier: Programming Language :: Python :: 3.8
Classifier: Programming Language :: Python :: 3.9
Classifier: Programming Language :: Python :: 3.10
Classifier: Programming Language :: Python :: 3.11
Classifier: Topic :: Utilities
Requires-Python: >=3.8
License-File: LICENSE.txt
